lightshap/__init__.py
lightshap/_version.py
lightshap/utils.py
lightshap/explainers/__init__.py
lightshap/explainers/_utils.py
lightshap/explainers/explain_any.py
lightshap/explainers/explain_tree.py
lightshap/explainers/kernel_utils.py
lightshap/explainers/parallel.py
lightshap/explainers/permutation_utils.py
lightshap/explainers/tests/test_explain_any.py
lightshap/explainers/tests/test_explain_tree.py
lightshap/explainers/tests/test_explainer_utils.py
lightshap/explainers/tests/test_kernel_utils.py
lightshap/explainers/tests/test_parallel.py
lightshap/explainers/tests/test_permutation_utils.py
lightshap/explanation/__init__.py
lightshap/explanation/_utils.py
lightshap/explanation/explanation.py
lightshap/explanation/explanationplotter.py
lightshap/explanation/tests/test_explanation.py
lightshap/explanation/tests/test_explanation_utils.py
lightshap/explanation/tests/test_plots.py
lightshap/tests/test_utils.py
lightshap-0.1.12.dist-info/METADATA
lightshap-0.1.12.dist-info/WHEEL
lightshap-0.1.12.dist-info/licenses/LICENSE
lightshap-0.1.12.dist-info/RECORD
