Metadata-Version: 2.4
Name: lightshap
Version: 0.1.12
Summary: A lightweight SHAP library
Project-URL: Homepage, https://github.com/mayer79/LightSHAP
Project-URL: Repository, https://github.com/mayer79/LightSHAP
Project-URL: Bug Tracker, https://github.com/mayer79/LightSHAP/issues
Author-email: Michael Mayer <mayermichael79@gmail.com>
Maintainer-email: Michael Mayer <mayermichael79@gmail.com>
License: MIT
License-File: LICENSE
Keywords: explainability,interpretability,machine-learning,shap,xai
Classifier: Development Status :: 4 - Beta
Classifier: Intended Audience :: Developers
Classifier: Intended Audience :: Science/Research
Classifier: License :: OSI Approved :: MIT License
Classifier: Operating System :: OS Independent
Classifier: Programming Language :: Python :: 3
Classifier: Programming Language :: Python :: 3.11
Classifier: Programming Language :: Python :: 3.12
Classifier: Programming Language :: Python :: 3.13
Classifier: Topic :: Scientific/Engineering
Classifier: Topic :: Scientific/Engineering :: Artificial Intelligence
Classifier: Topic :: Software Development :: Libraries :: Python Modules
Requires-Python: >=3.11
Requires-Dist: joblib>=1.3.0
Requires-Dist: matplotlib>=3.8.4
Requires-Dist: numpy>=2.0.0
Requires-Dist: pandas>=2.2.2
Requires-Dist: scipy>=1.13.1
Requires-Dist: tqdm>=4.67.0
Provides-Extra: all
Requires-Dist: catboost>=1.2.5; extra == 'all'
Requires-Dist: lightgbm>=4.4.0; extra == 'all'
Requires-Dist: mkdocs-material>=9.0.0; extra == 'all'
Requires-Dist: mkdocs>=1.5.0; extra == 'all'
Requires-Dist: mkdocstrings[python]>=0.24.0; extra == 'all'
Requires-Dist: polars>=1.1.0; extra == 'all'
Requires-Dist: pyarrow>=18.0.0; extra == 'all'
Requires-Dist: scikit-learn>=1.5.0; extra == 'all'
Requires-Dist: xgboost>=2.1.0; extra == 'all'
Provides-Extra: catboost
Requires-Dist: catboost>=1.2.5; extra == 'catboost'
Provides-Extra: dev
Requires-Dist: catboost>=1.2.5; extra == 'dev'
Requires-Dist: lightgbm>=4.4.0; extra == 'dev'
Requires-Dist: mkdocs-material>=9.0.0; extra == 'dev'
Requires-Dist: mkdocs>=1.5.0; extra == 'dev'
Requires-Dist: mkdocstrings[python]>=0.24.0; extra == 'dev'
Requires-Dist: polars>=1.1.0; extra == 'dev'
Requires-Dist: pre-commit>=2.20.0; extra == 'dev'
Requires-Dist: pyarrow>=18.0.0; extra == 'dev'
Requires-Dist: pytest-cov>=4.0.0; extra == 'dev'
Requires-Dist: pytest>=7.0.0; extra == 'dev'
Requires-Dist: ruff>=0.1.0; extra == 'dev'
Requires-Dist: scikit-learn>=1.5.0; extra == 'dev'
Requires-Dist: xgboost>=2.1.0; extra == 'dev'
Provides-Extra: docs
Requires-Dist: mkdocs-material>=9.0.0; extra == 'docs'
Requires-Dist: mkdocs>=1.5.0; extra == 'docs'
Requires-Dist: mkdocstrings[python]>=0.24.0; extra == 'docs'
Provides-Extra: lightgbm
Requires-Dist: lightgbm>=4.4.0; extra == 'lightgbm'
Provides-Extra: polars
Requires-Dist: polars>=1.1.0; extra == 'polars'
Requires-Dist: pyarrow>=18.0.0; extra == 'polars'
Provides-Extra: tree
Requires-Dist: catboost>=1.2.5; extra == 'tree'
Requires-Dist: lightgbm>=4.4.0; extra == 'tree'
Requires-Dist: xgboost>=2.1.0; extra == 'tree'
Provides-Extra: xgboost
Requires-Dist: xgboost>=2.1.0; extra == 'xgboost'
